agent_inspector/__init__.py
agent_inspector/cli.py
agent_inspector/defaults.py
agent_inspector/configs/__init__.py
agent_inspector/configs/base.yaml
agent_inspector-1.2.1.dist-info/METADATA
agent_inspector-1.2.1.dist-info/WHEEL
agent_inspector-1.2.1.dist-info/entry_points.txt
agent_inspector-1.2.1.dist-info/licenses/LICENSE
agent_inspector-1.2.1.dist-info/RECORD
