Metadata-Version: 2.4
Name: agent-inspector
Version: 1.2.1
Summary: CLI launcher for Cylestio Perimeter with default OpenAI and Anthropic configs
Author: Cylestio
License-Expression: MIT
License-File: LICENSE
Requires-Python: >=3.9
Requires-Dist: cylestio-perimeter>=2.4.0
Requires-Dist: pyyaml>=6.0.1
Requires-Dist: typer[all]>=0.12.3
